scurvebeta/__init__.py
scurvebeta/scurvebetatrue.py
s_curve_beta-0.1.2.dist-info/LICENSE
s_curve_beta-0.1.2.dist-info/METADATA
s_curve_beta-0.1.2.dist-info/WHEEL
s_curve_beta-0.1.2.dist-info/top_level.txt
s_curve_beta-0.1.2.dist-info/RECORD
