Metadata-Version: 2.1
Name: s-curve-beta
Version: 0.1.2
Summary: Efficient Python implementation of the smoothest S-curve robot motion planner ever
Home-page: https://github.com/hidoba/s-curve-beta
Author: Vladimir Grankovsky
Author-email: vladi@hidoba.com
License: Apache 2.0
Keywords: S-curve,motion planning,motion,robotics,robot,motor
License-File: LICENSE
Requires-Dist: numpy
